daqu/__init__.py
daqu/metrics.py
daqu-0.1.0.dist-info/WHEEL
daqu-0.1.0.dist-info/METADATA
daqu-0.1.0.dist-info/RECORD
